<?xml version="1.0" encoding="UTF-8"?>
<!DOCTYPE mapper
  PUBLIC "-//mybatis.org//DTD Mapper 3.0//EN"
  "http://mybatis.org/dtd/mybatis-3-mapper.dtd">
  
<mapper namespace="com.bit.board.dao.MemoDao">

	<insert id="writeMemo" parameterType="memoDto">
	insert into memo (mseq, seq, id, name, mcontent, mtime)
	values(memo_mseq.nextval, #{seq}, #{id}, #{name}, #{mcontent}, sysdate)
	</insert>
	
	<select id="listMemo" parameterType="int" resultType="memoDto">
	select mseq, seq, id, name, mcontent, mtime
	from memo
	where seq = #{seq}
	order by mseq
	</select>
	
	<update id="modifyMemo" parameterType="memoDto">
	update memo
	set mcontent = #{mcontent}
	where mseq=#{mseq}
	</update>
	
	<delete id="deleteMemo" parameterType="int">
	delete from memo
	where mseq = #{mseq}
	</delete>
	
</mapper>